wn_editor/__init__.py
wn_editor/editor.py
wn_editor-0.5.4.dist-info/LICENSE
wn_editor-0.5.4.dist-info/WHEEL
wn_editor-0.5.4.dist-info/METADATA
wn_editor-0.5.4.dist-info/RECORD
