Metadata-Version: 2.1
Name: wn-editor
Version: 0.5.4
Summary: An editor for wordnets, extending the popular 'wn' package.
Keywords: wn,wordnet,editor
Author-email: jannes@mlrjs.de
Requires-Python: >=3.9
Classifier: Intended Audience :: Information Technology
Classifier: Intended Audience :: Science/Research
Classifier: Operating System :: OS Independent
Classifier: Programming Language :: Python :: 3
Classifier: Programming Language :: Python
Classifier: Typing :: Typed
Classifier: Development Status :: 3 - Alpha
Classifier: Environment :: Console
Classifier: Intended Audience :: Developers
Classifier: License :: OSI Approved :: MIT License
Classifier: Programming Language :: Python :: 3.10
Classifier: Topic :: Scientific/Engineering :: Information Analysis
Classifier: Topic :: Software Development :: Libraries :: Python Modules
Classifier: Topic :: Text Processing :: Linguistic
Project-URL: documentation, https://github.com/Hypercookie/wn-editor
Project-URL: homepage, https://github.com/Hypercookie/wn-editor
